RenderKit/__init__.py
RenderKit/custom_widgets/__init__.py
RenderKit/custom_widgets/textarea.py
RenderKit-1.0.1.dist-info/METADATA
RenderKit-1.0.1.dist-info/WHEEL
RenderKit-1.0.1.dist-info/top_level.txt
RenderKit-1.0.1.dist-info/RECORD
