Metadata-Version: 2.1
Name: RenderKit
Version: 1.0.1
Summary: build desktop apps using HTML and Python.
Home-page: https://github.com/cj-praveen/RenderKit/
Keywords: RenderKit
Requires-Python: >=3.9
Requires-Dist: bs4 ==0.0.2
Requires-Dist: pillow ==10.4.0
Requires-Dist: httpx ==0.27.0
